GaPy/__init__.py
GaPy/binary_mutate.py
GaPy/chromosome.py
GaPy/elite.py
GaPy/event.py
GaPy/event_args.py
GaPy/exceptions.py
GaPy/ga.py
GaPy/genetic_operator.py
GaPy/parent_selection_method.py
GaPy/population.py
GaPy/replacement_method.py
GaPy/single_point_crossover.py
tests/__init__.py
tests/test_binaryMutate.py
tests/test_elite.py
tests/test_ga.py
tests/test_geneticOperator.py
tests/test_population.py
tests/test_singlePointCrossover.py
GaFramework-0.0.2.dist-info/LICENSE
GaFramework-0.0.2.dist-info/METADATA
GaFramework-0.0.2.dist-info/WHEEL
GaFramework-0.0.2.dist-info/top_level.txt
GaFramework-0.0.2.dist-info/RECORD
